aoiksixyio/aoiksixyioexp.py
aoiksixyio/aoiksixyio_.py
aoiksixyio/__init__.py
AoikSixyIO-0.1.0.dist-info/DESCRIPTION.rst
AoikSixyIO-0.1.0.dist-info/entry_points.txt
AoikSixyIO-0.1.0.dist-info/METADATA
AoikSixyIO-0.1.0.dist-info/metadata.json
AoikSixyIO-0.1.0.dist-info/RECORD
AoikSixyIO-0.1.0.dist-info/top_level.txt
AoikSixyIO-0.1.0.dist-info/WHEEL
