Metadata-Version: 2.0
Name: AoikSixyIO
Version: 0.1.0
Summary: Make Python string encoding and IO code 2*3 compatible, mess-free, and error-proof.
Home-page: https://github.com/AoiKuiyuyou/AoikSixyIO
Author: Aoi.Kuiyuyou
Author-email: aoi.kuiyuyou@google.com
License: MIT
Platform: UNKNOWN
Classifier: Development Status :: 3 - Alpha
Classifier: Intended Audience :: Developers
Classifier: License :: OSI Approved :: MIT License
Classifier: Operating System :: OS Independent
Classifier: Programming Language :: Python :: 2
Classifier: Programming Language :: Python :: 2.7
Classifier: Programming Language :: Python :: 3
Classifier: Programming Language :: Python :: 3.3
Classifier: Programming Language :: Python :: 3.4
